fractionalcover3/__init__.py
fractionalcover3/compute_fractionalcover.py
fractionalcover3/compute_seasonalfcover.py
fractionalcover3/data.py
fractionalcover3/fc_model_fit.py
fractionalcover3/qv_fractionalcover_sentinel2.py
fractionalcover3/qv_seasonalfcover_sentinel2.py
fractionalcover3/unmixcover.py
fractionalcover3/pkgdata/cfmsre_sub_20200510_abam5.img
fractionalcover3/pkgdata/cfmsre_sub_20200510_abbm5.img
fractionalcover3/pkgdata/fcModel_256x128x256.tflite
fractionalcover3/pkgdata/fcModel_256x64x256.tflite
fractionalcover3/pkgdata/fcModel_32x32x32.tflite
fractionalcover3/pkgdata/fcModel_64x64x64.tflite
fractionalcover3/pkgdata/l7tmre_sub_20190511_dbgm3.img
fractionalcover3/pkgdata/training_data.json
fractionalcover3-1.0.10.dist-info/AUTHORS.rst
fractionalcover3-1.0.10.dist-info/LICENSE.txt
fractionalcover3-1.0.10.dist-info/METADATA
fractionalcover3-1.0.10.dist-info/WHEEL
fractionalcover3-1.0.10.dist-info/entry_points.txt
fractionalcover3-1.0.10.dist-info/top_level.txt
fractionalcover3-1.0.10.dist-info/RECORD
